autobots/__init__.py
tests/__init__.py
autobots-0.0.1.dist-info/LICENSE-MIT
autobots-0.0.1.dist-info/METADATA
autobots-0.0.1.dist-info/WHEEL
autobots-0.0.1.dist-info/top_level.txt
autobots-0.0.1.dist-info/RECORD
