Metadata-Version: 2.1
Name: autobots
Version: 0.0.1
Summary: transformers based nlp library
Home-page: https://github.com/maxent-ai/autobots
Author: maxentlabs.ai team
Author-email: royalkingpin@gmail.com
Maintainer: maxentlabs.ai
Maintainer-email: royalkingpin@gmail.com
License: MIT
Platform: UNKNOWN
Classifier: Development Status :: 4 - Beta
Classifier: Intended Audience :: Developers
Classifier: License :: OSI Approved :: MIT License
Classifier: Natural Language :: English
Classifier: Operating System :: OS Independent
Classifier: Programming Language :: Python :: 3.6
Classifier: Programming Language :: Python :: Implementation :: CPython
